{"standConfig":[{"idBirds":[7,3,0,8,3],"standData":{"type":1,"numSlot":5},"side":-1},{"idBirds":[9,8,1,5,3],"standData":{"type":1,"numSlot":5},"side":-1},{"idBirds":[3,4,7,0,6],"standData":{"type":1,"numSlot":5},"side":-1},{"idBirds":[7,2,5,1,4],"standData":{"type":1,"numSlot":5},"side":1},{"idBirds":[],"standData":{"type":1,"numSlot":5},"side":1},{"idBirds":[2,6,8,5,6],"standData":{"type":1,"numSlot":5},"side":1},{"idBirds":[7,1,9,9,2],"standData":{"type":1,"numSlot":5},"side":-1},{"idBirds":[2,6,7,4,2],"standData":{"type":1,"numSlot":5},"side":1},{"idBirds":[6,8,4,9,3],"standData":{"type":1,"numSlot":5},"side":-1},{"idBirds":[5,8,0,1,0],"standData":{"type":1,"numSlot":5},"side":-1},{"idBirds":[9,0,5,4,1],"standData":{"type":1,"numSlot":5},"side":1},{"idBirds":[],"standData":{"type":1,"numSlot":5},"side":1}]}